predicode/__init__.py
predicode/datasets/__init__.py
predicode/datasets/cifar10.py
predicode/datasets/imagedata.py
predicode/simulations/__init__.py
predicode-0.0.0.9000.dist-info/DESCRIPTION.rst
predicode-0.0.0.9000.dist-info/METADATA
predicode-0.0.0.9000.dist-info/RECORD
predicode-0.0.0.9000.dist-info/WHEEL
predicode-0.0.0.9000.dist-info/metadata.json
predicode-0.0.0.9000.dist-info/top_level.txt
